LICENSE.txt
MANIFEST.in
README.md
setup.py
tosr0x.py
tosr0x.egg-info/PKG-INFO
tosr0x.egg-info/SOURCES.txt
tosr0x.egg-info/dependency_links.txt
tosr0x.egg-info/requires.txt
tosr0x.egg-info/top_level.txt