Metadata-Version: 1.0
Name: tosr0x
Version: 0.6.1
Summary: An interface to tinyos.com TOSR0x relay modules.
Home-page: https://github.com/amorphic/tosr0x
Author: James Stewart
Author-email: jstewart101@gmail.com
License: LICENSE.txt
Platform: UNKNOWN
